vascusim/__init__.py
vascusim/_version.py
vascusim/config.py
vascusim/data/__init__.py
vascusim/data/conversion.py
vascusim/data/dataset.py
vascusim/data/transforms.py
vascusim/io/__init__.py
vascusim/io/cache.py
vascusim/io/formats.py
vascusim/io/streaming.py
vascusim/io/vtk_utils.py
vascusim/processing/__init__.py
vascusim/processing/domain.py
vascusim/processing/geometry.py
vascusim/processing/parallel.py
vascusim/processing/preprocessing.py
vascusim/utils/__init__.py
vascusim/utils/metadata.py
vascusim/utils/visualization.py
vascusim-0.2.0.dist-info/METADATA
vascusim-0.2.0.dist-info/WHEEL
vascusim-0.2.0.dist-info/top_level.txt
vascusim-0.2.0.dist-info/RECORD
