Metadata-Version: 2.4
Name: vascusim
Version: 0.2.0
Summary: Dataset package for cardiovascular simulations
Author-email: Wenzhuo Xu <wzxu@cmu.edu>
Project-URL: Homepage, https://github.com/biosimmlab/vascusim
Project-URL: Issues, https://github.com/biosimmlab/vascusim/issues
Project-URL: Documentation, https://vascusim.readthedocs.io
Classifier: Development Status :: 3 - Alpha
Classifier: Intended Audience :: Science/Research
Classifier: License :: OSI Approved :: MIT License
Classifier: Programming Language :: Python :: 3
Classifier: Programming Language :: Python :: 3.10
Classifier: Programming Language :: Python :: 3.11
Classifier: Programming Language :: Python :: 3.12
Classifier: Topic :: Scientific/Engineering
Requires-Python: >=3.9
Requires-Dist: numpy>=1.21.0
Requires-Dist: torch>=1.13.0
Requires-Dist: torch-geometric>=2.3.0
Requires-Dist: requests>=2.28.0
Requires-Dist: vtk>=9.2.0
Requires-Dist: matplotlib>=3.6.0
Requires-Dist: tqdm>=4.64.0
Requires-Dist: pyvista>=0.37.0
Requires-Dist: huggingface_hub>=0.13.0
Requires-Dist: h5py>=3.8.0
Requires-Dist: synology-api>=0.8.0
Provides-Extra: dev
Requires-Dist: pytest>=7.0; extra == "dev"
Requires-Dist: pytest-cov>=4.0; extra == "dev"
Requires-Dist: black>=23.0; extra == "dev"
Requires-Dist: isort>=5.12; extra == "dev"
Requires-Dist: flake8>=6.0; extra == "dev"
Requires-Dist: mypy>=1.0; extra == "dev"
Provides-Extra: docs
Requires-Dist: sphinx>=7.0; extra == "docs"
Requires-Dist: sphinx-rtd-theme>=1.2; extra == "docs"
Requires-Dist: sphinx-copybutton>=0.5; extra == "docs"
Requires-Dist: sphinx-autodoc-typehints>=1.22; extra == "docs"
Provides-Extra: smb
Requires-Dist: pysmb>=1.2.8; extra == "smb"
